conveiro/__init__.py
conveiro/cdfs.py
conveiro/cli.py
conveiro/deep_dream.py
conveiro/utils.py
conveiro-0.2.1.dist-info/LICENSE
conveiro-0.2.1.dist-info/METADATA
conveiro-0.2.1.dist-info/WHEEL
conveiro-0.2.1.dist-info/entry_points.txt
conveiro-0.2.1.dist-info/top_level.txt
conveiro-0.2.1.dist-info/RECORD
