Metadata-Version: 2.1
Name: conveiro
Version: 0.2.1
Summary: Visualization of filters in convolutional neural networks
Home-page: https://github.com/showmax/conveiro
Author: The ShowmaxLab & Showmax teams
Author-email: oss+conveiro@showmax.com
License: Apache License, Version 2.0
Keywords: CNN,neural networks,deep dream,visualization
Platform: any
Classifier: Development Status :: 3 - Alpha
Classifier: Intended Audience :: Developers
Classifier: Intended Audience :: Science/Research
Classifier: License :: OSI Approved :: Apache Software License
Classifier: Programming Language :: Python :: 3
Classifier: Topic :: Scientific/Engineering
Classifier: Topic :: Software Development :: Libraries :: Python Modules
Requires-Python: ~=3.4
License-File: LICENSE
Requires-Dist: numpy
Requires-Dist: matplotlib
Requires-Dist: scipy
Requires-Dist: pillow
Provides-Extra: cli
Requires-Dist: tensornets ; extra == 'cli'
Requires-Dist: click ; extra == 'cli'
Requires-Dist: graphviz ; extra == 'cli'
Provides-Extra: cpu
Requires-Dist: tensorflow <2.0 ; extra == 'cpu'
Provides-Extra: examples
Requires-Dist: tensornets ; extra == 'examples'
Provides-Extra: gpu
Requires-Dist: tensorflow-gpu <2.0 ; extra == 'gpu'
